LICENSE
MANIFEST.in
README.md
setup.py
django_ldap_academia_ou_manager.egg-info/PKG-INFO
django_ldap_academia_ou_manager.egg-info/SOURCES.txt
django_ldap_academia_ou_manager.egg-info/dependency_links.txt
django_ldap_academia_ou_manager.egg-info/requires.txt
django_ldap_academia_ou_manager.egg-info/top_level.txt
ldap_peoples/__init__.py
ldap_peoples/admin.py
ldap_peoples/admin_actions.py
ldap_peoples/admin_filters.py
ldap_peoples/admin_utils.py
ldap_peoples/apps.py
ldap_peoples/auth.py
ldap_peoples/form_fields.py
ldap_peoples/forms.py
ldap_peoples/hash_functions.py
ldap_peoples/idem_affiliation_mapping.py
ldap_peoples/ldap_utils.py
ldap_peoples/ldif.py
ldap_peoples/model_fields.py
ldap_peoples/models.py
ldap_peoples/serializers.py
ldap_peoples/settings.py
ldap_peoples/tests.py
ldap_peoples/urls.py
ldap_peoples/version.py
ldap_peoples/views.py
ldap_peoples/widgets.py
ldap_peoples/migrations/__init__.py
ldap_peoples/static/js/given_display_name_autofill.js
ldap_peoples/static/js/textarea-autosize.js
ldap_peoples/templates/change_form.html
ldap_peoples/templates/change_list.html
ldap_peoples/templates/filters/custom_search.html