Metadata-Version: 2.1
Name: django-ldap-academia-ou-manager
Version: 0.9.2.post1
Summary: Django Admin manager for Academia Users with eduPerson schema and SCHAC (SCHema for ACademia).
Home-page: https://github.com/peppelinux/django-ldap-academia-ou-manager
Author: Giuseppe De Marco
Author-email: giuseppe.demarco@unical.it
License: BSD
Platform: UNKNOWN
Classifier: Development Status :: 5 - Production/Stable
Classifier: License :: OSI Approved :: BSD License
Classifier: Programming Language :: Python :: 3 :: Only
Classifier: Operating System :: POSIX :: Linux
